setup.py
glemon/__init__.py
glemon/__version__.py
glemon/cachedquery.py
glemon/config.py
glemon/document.py
glemon/expr.py
glemon/fields.py
glemon/loadcheck.py
glemon/loadfile.py
glemon/paginate.py
glemon/query.py
glemon/shadow.py
glemon.egg-info/PKG-INFO
glemon.egg-info/SOURCES.txt
glemon.egg-info/dependency_links.txt
glemon.egg-info/entry_points.txt
glemon.egg-info/requires.txt
glemon.egg-info/top_level.txt