Metadata-Version: 1.0
Name: glemon
Version: 0.1.1a43
Summary: glemon
Home-page: https://github.com/huangtao-sh/lemon.git
Author: 黄涛
Author-email: hunto@163.com
License: GPL
Platform: any
